{
  "version": 1,
  "shardId": "01",
  "images": [
    {
      "id": "667122ed",
      "filename": "crawl_src_mqwjeg06_t_1782719300286.jpg",
      "path": "uploads/2026/06/a3db8e34.jpg",
      "size": 600938,
      "width": 947,
      "height": 1339,
      "mimeType": "image/jpeg",
      "hash": "48f309a781fc12ba860f09bdc4cf00334e6dfb1c1804bf4b0559704f97e8eca6",
      "uploaderLogin": "system",
      "createdAt": "2026-06-29T07:48:49.256Z",
      "isPublic": true
    },
    {
      "id": "2467a69b",
      "filename": "crawl_src_mqwjeg05_1_1782719217657.webp",
      "path": "uploads/2026/06/cd99b6ce.webp",
      "size": 322184,
      "width": 1300,
      "height": 2021,
      "mimeType": "image/webp",
      "hash": "fa0a489340b203b1b9580382264b1d866c96dc13e4ecc8c7c0464aa65748c9d0",
      "uploaderLogin": "system",
      "createdAt": "2026-06-29T07:47:03.767Z",
      "isPublic": true
    },
    {
      "id": "2d3eb3f7",
      "filename": "crawl_src_mqwjeg05_1_1782718662078.webp",
      "path": "uploads/2026/06/c8c751da.webp",
      "size": 507734,
      "width": 2606,
      "height": 4000,
      "mimeType": "image/webp",
      "hash": "d2456f495563496bd6f304bbd1ce88871d2ee93f1261738a9bb82aa147a20e64",
      "uploaderLogin": "system",
      "createdAt": "2026-06-29T07:37:59.269Z",
      "isPublic": true
    },
    {
      "id": "efc53201",
      "filename": "crawl_src_mqwjeg06_t_1782718456048.jpg",
      "path": "uploads/2026/06/a5b6a47a.jpg",
      "size": 620599,
      "width": 1400,
      "height": 2000,
      "mimeType": "image/jpeg",
      "hash": "79339ecd42e9788254b63fd86563eea9c31cf3614942656be9efd9b9c5bb3d22",
      "uploaderLogin": "system",
      "createdAt": "2026-06-29T07:34:36.685Z",
      "isPublic": true
    },
    {
      "id": "2ea37be1",
      "filename": "crawl_src_new_003_1782718439332.webp",
      "path": "uploads/2026/06/02e755dd.webp",
      "size": 256870,
      "width": 1450,
      "height": 2048,
      "mimeType": "image/webp",
      "hash": "f414cb7ba3d44b25478bece1a307e78c0d638bb220e2e3bcf874218b2c5cefd1",
      "uploaderLogin": "system",
      "createdAt": "2026-06-29T07:34:04.536Z",
      "isPublic": true
    },
    {
      "id": "90906414",
      "filename": "crawl_src_mqwjeg05_1_1782717653878.webp",
      "path": "uploads/2026/06/78f5958c.webp",
      "size": 324386,
      "width": 1980,
      "height": 3101,
      "mimeType": "image/webp",
      "hash": "ea56f3b327a4972de66f654dca93a28da988bf09142bc4440fde96731289577b",
      "uploaderLogin": "system",
      "createdAt": "2026-06-29T07:21:09.902Z",
      "isPublic": true
    },
    {
      "id": "41536745",
      "filename": "crawl_src_new_003_1782717336460.webp",
      "path": "uploads/2026/06/b5b27cda.webp",
      "size": 396062,
      "width": 2400,
      "height": 3600,
      "mimeType": "image/webp",
      "hash": "990fdc3223f68c0d40c78dd1680efce28ef9cdf1b442f70b816520e1c6c44a96",
      "uploaderLogin": "system",
      "createdAt": "2026-06-29T07:15:38.516Z",
      "isPublic": true
    },
    {
      "id": "a77fd5bf",
      "filename": "crawl_src_mqwjeg06_t_1782715296944.png",
      "path": "uploads/2026/06/8741267e.png",
      "size": 2966067,
      "mimeType": "image/png",
      "hash": "99a9967e8f79fd2db7f00ee56133d565d26b0f8f94916cbcea6b635721960565",
      "uploaderLogin": "system",
      "createdAt": "2026-06-29T06:41:51.946Z",
      "isPublic": true
    },
    {
      "id": "7a0b8be3",
      "filename": "crawl_src_mqwjeg06_t_1782715293103.png",
      "path": "uploads/2026/06/358f25e3.png",
      "size": 3475051,
      "mimeType": "image/png",
      "hash": "9ff5cd0861990ac56c3d37b0d13b5d3cb305724b36dc49eb92c50f908bb17ca1",
      "uploaderLogin": "system",
      "createdAt": "2026-06-29T06:41:45.712Z",
      "isPublic": true
    },
    {
      "id": "8c51ca97",
      "filename": "crawl_src_mqwjeg06_t_1782715282902.jpg",
      "path": "uploads/2026/06/89888dd3.jpg",
      "size": 1440299,
      "mimeType": "image/jpeg",
      "hash": "d7a59cd6dd82327c052b146c505990d35c9b15a8eeee8a9de7ae4eef642c68ea",
      "uploaderLogin": "system",
      "createdAt": "2026-06-29T06:41:38.109Z",
      "isPublic": true
    },
    {
      "id": "23032a79",
      "filename": "crawl_src_new_003_1782711846724.webp",
      "path": "uploads/2026/06/fc659af9.webp",
      "size": 143914,
      "width": 1227,
      "height": 1700,
      "mimeType": "image/webp",
      "hash": "6d390d06a2b82d087722fb00c1c961740fa842be27344af97692db26c16e99f1",
      "uploaderLogin": "system",
      "createdAt": "2026-06-29T05:44:06.735Z",
      "isPublic": true
    },
    {
      "id": "41c65d08",
      "filename": "crawl_src_new_003_1782711376467.webp",
      "path": "uploads/2026/06/25fecbce.webp",
      "size": 110928,
      "width": 1448,
      "height": 2048,
      "mimeType": "image/webp",
      "hash": "bb13b2d0e4ffb96eca4383c7b0b90432b34314b1e88873cbd6d6fc23a82c75e4",
      "uploaderLogin": "system",
      "createdAt": "2026-06-29T05:36:27.801Z",
      "isPublic": true
    },
    {
      "id": "4ad46010",
      "filename": "crawl_src_mqwjeg05_1_1782711330644.webp",
      "path": "uploads/2026/06/b2468769.webp",
      "size": 243016,
      "width": 1528,
      "height": 2160,
      "mimeType": "image/webp",
      "hash": "39a7462dd078a69969d7d4ef36ea8324bef7ae4e7570d19ee98f1bef410943de",
      "uploaderLogin": "system",
      "createdAt": "2026-06-29T05:35:38.654Z",
      "isPublic": true
    },
    {
      "id": "7e23cfa2",
      "filename": "pixiv_145541970_p0.jpg",
      "path": "uploads/2026/06/41203c97.jpg",
      "size": 686384,
      "width": 850,
      "height": 1200,
      "mimeType": "image/jpeg",
      "hash": "7706fc3ac621790ff4d7bf02080f18479a72d80bad0dff72a736588d1986add8",
      "uploaderLogin": "system",
      "createdAt": "2026-06-29T04:39:23.858Z",
      "isPublic": true,
      "title": "デュース誕生日おめでとう漫画",
      "tags": [
        "twst夢",
        "あ、来た来…え?警察呼ぶえ?警察が共犯??",
        "島の砂浜に秒で出来たオブジェ",
        "どう見てもやばい絵面になってしまいながら運ばれる",
        "最初から最後までクライマックス",
        "陶芸家な王子",
        "理解はあるが常識が外れたお巡りさん",
        "陶芸家のレオナ先輩",
        "可哀想なおまわりさん",
        "中からは開けられないようになってるんだ!"
      ],
      "sourceProvider": "pixiv",
      "sourceId": "145541970_p0",
      "sourcePageUrl": "https://www.pixiv.net/artworks/145541970",
      "sourceCreatedAt": "2026-06-02T21:03:17.000Z"
    },
    {
      "id": "98e2e12d",
      "filename": "pixiv_146541599_p0.jpg",
      "path": "uploads/2026/06/a44e980a.jpg",
      "size": 1544797,
      "width": 792,
      "height": 1200,
      "mimeType": "image/jpeg",
      "hash": "279fc10e86a1ba0c7dead4ca0b1cd5882b91078e602cb97932371b1dc2cf16fc",
      "uploaderLogin": "system",
      "createdAt": "2026-06-29T04:38:05.618Z",
      "isPublic": true,
      "title": "Elegant",
      "tags": [
        "原神",
        "GenshinImpact",
        "サンドローネ(原神)",
        "原神1000users入り"
      ],
      "sourceProvider": "pixiv",
      "sourceId": "146541599_p0",
      "sourcePageUrl": "https://www.pixiv.net/artworks/146541599",
      "sourceCreatedAt": "2026-06-27T16:04:07.000Z"
    },
    {
      "id": "0229864d",
      "filename": "crawl_src_new_003_1782707424417.webp",
      "path": "uploads/2026/06/4cef89f5.webp",
      "size": 132240,
      "width": 880,
      "height": 1200,
      "mimeType": "image/webp",
      "hash": "e44ca53387fb615136332a5bf2c3fdee82855a1bc3689959ddf5c4efded64ad5",
      "uploaderLogin": "system",
      "createdAt": "2026-06-29T04:30:31.661Z",
      "isPublic": true
    },
    {
      "id": "f956fa1c",
      "filename": "crawl_src_mqwjeg05_1_1782705360907.webp",
      "path": "uploads/2026/06/cae57b61.webp",
      "size": 498038,
      "width": 1884,
      "height": 2664,
      "mimeType": "image/webp",
      "hash": "2620f38bd2e39fdc44c0d4049f3063d7cecd699a3f63e6ebf18c4842e4870df0",
      "uploaderLogin": "system",
      "createdAt": "2026-06-29T03:56:20.739Z",
      "isPublic": true
    },
    {
      "id": "2dcd3639",
      "filename": "crawl_src_mqwjeg06_t_1782705250625.jpg",
      "path": "uploads/2026/06/8f9c2374.jpg",
      "size": 859517,
      "width": 3500,
      "height": 3714,
      "mimeType": "image/jpeg",
      "hash": "8a29d0a4771736407e0afea9ede9cf559a511f2b75fc0be2c3cd1488d992bc14",
      "uploaderLogin": "system",
      "createdAt": "2026-06-29T03:54:31.675Z",
      "isPublic": true
    },
    {
      "id": "019ceb86",
      "filename": "crawl_builtin_sakura_api_1782704893471.webp",
      "path": "uploads/2026/06/cb95ee88.webp",
      "size": 140084,
      "width": 1000,
      "height": 1575,
      "mimeType": "image/webp",
      "hash": "aecaddff027e0417075bc16d153ce806208779f11270a0e0142ddd63248e7cc6",
      "uploaderLogin": "system",
      "createdAt": "2026-06-29T03:48:15.695Z",
      "isPublic": true
    },
    {
      "id": "d3e98ba6",
      "filename": "crawl_src_mqwjeg05_8_1782678639634.jpg",
      "path": "uploads/2026/06/2aa86bb8.jpg",
      "size": 615336,
      "width": 1920,
      "height": 1079,
      "mimeType": "image/jpeg",
      "hash": "69df1e8e6389096d9ba2c00345b369cf3a7894e58d5937576e926d019105d82f",
      "uploaderLogin": "system",
      "createdAt": "2026-06-28T20:30:50.904Z",
      "isPublic": true
    },
    {
      "id": "eacb51e0",
      "filename": "crawl_src_new_002_1782675950090.webp",
      "path": "uploads/2026/06/d3cbf720.webp",
      "size": 195568,
      "width": 2000,
      "height": 1048,
      "mimeType": "image/webp",
      "hash": "7da0f53e9be1ec6ccc340dc2d3023ba87be8604886d7d7530e020bab0849ba8a",
      "uploaderLogin": "system",
      "createdAt": "2026-06-28T19:45:53.855Z",
      "isPublic": true
    },
    {
      "id": "3e988803",
      "filename": "crawl_src_mqwjeg05_1_1782675905396.webp",
      "path": "uploads/2026/06/1f0cdcda.webp",
      "size": 179318,
      "width": 1417,
      "height": 2126,
      "mimeType": "image/webp",
      "hash": "e577301abb13b28f11aa8cedb7679c06d5816f2a2df3e37882faaa08f8750726",
      "uploaderLogin": "system",
      "createdAt": "2026-06-28T19:45:16.950Z",
      "isPublic": true
    },
    {
      "id": "b3e34bdd",
      "filename": "crawl_src_mqwjeg06_t_1782675835318.jpg",
      "path": "uploads/2026/06/67bd38bd.jpg",
      "size": 902949,
      "width": 1281,
      "height": 1047,
      "mimeType": "image/jpeg",
      "hash": "76c88f4e5283364dac007004204cd8c3984879ff0ea5ac70f0ea7361fa14452d",
      "uploaderLogin": "system",
      "createdAt": "2026-06-28T19:44:08.517Z",
      "isPublic": true
    },
    {
      "id": "244bb730",
      "filename": "crawl_src_mqwjeg05_1_1782675678836.webp",
      "path": "uploads/2026/06/e0dcf104.webp",
      "size": 616318,
      "width": 2886,
      "height": 4448,
      "mimeType": "image/webp",
      "hash": "edfc971fb68ef0c1bd22ded269eae5c43f68c285a3eeef4eefb1678eeafb7bb3",
      "uploaderLogin": "system",
      "createdAt": "2026-06-28T19:41:30.744Z",
      "isPublic": true
    },
    {
      "id": "7a0b58a6",
      "filename": "crawl_src_new_003_1782675553603.webp",
      "path": "uploads/2026/06/ba0640af.webp",
      "size": 639564,
      "width": 3091,
      "height": 4096,
      "mimeType": "image/webp",
      "hash": "a62e69880da51dc4388a96e18c23b910502a1f5afb689da75730c377dc1b37b7",
      "uploaderLogin": "system",
      "createdAt": "2026-06-28T19:39:18.738Z",
      "isPublic": true
    },
    {
      "id": "a8ec31cd",
      "filename": "crawl_src_new_004_1782675340962.webp",
      "path": "uploads/2026/06/251e0349.webp",
      "size": 408672,
      "width": 3500,
      "height": 2333,
      "mimeType": "image/webp",
      "hash": "c4bb32b7065879c22162cc4ac7e20a5d72c5a0d3e326461651d8bd113e5b267e",
      "uploaderLogin": "system",
      "createdAt": "2026-06-28T19:35:43.931Z",
      "isPublic": true
    },
    {
      "id": "0af252cc",
      "filename": "crawl_src_new_003_1782674812610.webp",
      "path": "uploads/2026/06/23aa34d9.webp",
      "size": 105264,
      "width": 807,
      "height": 1173,
      "mimeType": "image/webp",
      "hash": "922f4f0f5f26d022484c629a9c0aadb1a7215bc678e35c5be989fc331e448ae4",
      "uploaderLogin": "system",
      "createdAt": "2026-06-28T19:27:05.314Z",
      "isPublic": true
    },
    {
      "id": "845a725b",
      "filename": "pixiv_146483589_p0.jpg",
      "path": "uploads/2026/06/61af156f.jpg",
      "size": 759056,
      "width": 849,
      "height": 1200,
      "mimeType": "image/jpeg",
      "hash": "596038f703e2ccf4074828bbb58905d094fed75729c2378b92aa87eb91a205c5",
      "uploaderLogin": "system",
      "createdAt": "2026-06-28T18:49:43.997Z",
      "isPublic": true,
      "title": "寝起きサンドローネ",
      "tags": [
        "原神",
        "GenshinImpact",
        "Sandrone",
        "サンドローネ(原神)",
        "コロサン",
        "おっぱい"
      ],
      "sourceProvider": "pixiv",
      "sourceId": "146483589_p0",
      "sourcePageUrl": "https://www.pixiv.net/artworks/146483589",
      "sourceCreatedAt": "2026-06-26T12:02:18.000Z"
    },
    {
      "id": "ef00691f",
      "filename": "crawl_src_new_003_1782671829448.webp",
      "path": "uploads/2026/06/3f796c83.webp",
      "size": 93376,
      "width": 1000,
      "height": 1300,
      "mimeType": "image/webp",
      "hash": "a555ef462f571252e0b61797e2c14585f352c6adecacbbe8d7028735bdf1598e",
      "uploaderLogin": "system",
      "createdAt": "2026-06-28T18:37:17.977Z",
      "isPublic": true
    },
    {
      "id": "34574d9e",
      "filename": "crawl_src_new_003_1782671743709.webp",
      "path": "uploads/2026/06/4abdced9.webp",
      "size": 754450,
      "width": 3000,
      "height": 4500,
      "mimeType": "image/webp",
      "hash": "27ebe3133e72994f8f1413b1d12d53edf6f639a7e7b5010841d0491cd7bc33f6",
      "uploaderLogin": "system",
      "createdAt": "2026-06-28T18:35:47.063Z",
      "isPublic": true
    },
    {
      "id": "525a06f1",
      "filename": "crawl_src_new_003_1782671499707.webp",
      "path": "uploads/2026/06/079f2157.webp",
      "size": 565802,
      "width": 2312,
      "height": 3143,
      "mimeType": "image/webp",
      "hash": "54e7bbb959c8650bd3b94494a51d354a492189e785f5dfa43e616861d2fd2467",
      "uploaderLogin": "system",
      "createdAt": "2026-06-28T18:31:42.809Z",
      "isPublic": true
    },
    {
      "id": "cbb84c4d",
      "filename": "crawl_src_new_004_1782671348354.webp",
      "path": "uploads/2026/06/2fa2231a.webp",
      "size": 190594,
      "width": 1980,
      "height": 1114,
      "mimeType": "image/webp",
      "hash": "2c8d9ea8a3ac861373d24c731b56e6672885ee7180a91dee3ffe612215c3a35f",
      "uploaderLogin": "system",
      "createdAt": "2026-06-28T18:29:12.689Z",
      "isPublic": true
    },
    {
      "id": "0166c5c7",
      "filename": "crawl_src_mqwjeg06_t_1782671297010.jpg",
      "path": "uploads/2026/06/be8b549d.jpg",
      "size": 807730,
      "width": 3435,
      "height": 3312,
      "mimeType": "image/jpeg",
      "hash": "945a5365f7f13d8915ec3098fec9fee8896bf1c57f9b7b77aabe38c018367ab1",
      "uploaderLogin": "system",
      "createdAt": "2026-06-28T18:28:39.592Z",
      "isPublic": true
    },
    {
      "id": "d60c4da9",
      "filename": "crawl_src_mqwjeg06_t_1782671208093.png",
      "path": "uploads/2026/06/5693b6f8.png",
      "size": 2082376,
      "width": 1439,
      "height": 2560,
      "mimeType": "image/png",
      "hash": "8cdd14fb61decd5796c3abeb39118697cbe5f94ab516986b25a5811a1aeecdae",
      "uploaderLogin": "system",
      "createdAt": "2026-06-28T18:27:11.859Z",
      "isPublic": true
    },
    {
      "id": "059d2233",
      "filename": "crawl_src_mqwjeg06_t_1782668639193.jpg",
      "path": "uploads/2026/06/e4c7f87b.jpg",
      "size": 3388560,
      "width": 2084,
      "height": 2947,
      "mimeType": "image/jpeg",
      "hash": "57f3621162c369fd3c3191cc11b11b6c6ad7a7a6d7476da49931355924b7cb56",
      "uploaderLogin": "system",
      "createdAt": "2026-06-28T17:44:29.080Z",
      "isPublic": true
    },
    {
      "id": "64b61b08",
      "filename": "crawl_src_mqwjeg05_1_1782668562888.webp",
      "path": "uploads/2026/06/e5ef2a5d.webp",
      "size": 373664,
      "width": 2480,
      "height": 3508,
      "mimeType": "image/webp",
      "hash": "84e0584e06dadfe04383e0695b43c17e11270afb2636871fbf4da7ca3d5795f0",
      "uploaderLogin": "system",
      "createdAt": "2026-06-28T17:42:50.066Z",
      "isPublic": true
    },
    {
      "id": "f376549f",
      "filename": "crawl_src_mqwjeg06_t_1782668201325.jpg",
      "path": "uploads/2026/06/5d50bc89.jpg",
      "size": 546197,
      "width": 1080,
      "height": 1888,
      "mimeType": "image/jpeg",
      "hash": "1c376425893b11227bc1b4676ddd56e0f38b5fed2801c3cd591b14a7ac94bd85",
      "uploaderLogin": "system",
      "createdAt": "2026-06-28T17:36:59.542Z",
      "isPublic": true
    },
    {
      "id": "30fafdfc",
      "filename": "crawl_src_mqwjeg05_1_1782668002574.webp",
      "path": "uploads/2026/06/db8185c5.webp",
      "size": 143542,
      "width": 1274,
      "height": 1800,
      "mimeType": "image/webp",
      "hash": "2c3c227ba124f1d7ebb1e778a2aa61d4ab67e11015eaee299cfbd72ef9350fc5",
      "uploaderLogin": "system",
      "createdAt": "2026-06-28T17:33:36.901Z",
      "isPublic": true
    },
    {
      "id": "206a41b4",
      "filename": "pixiv_146298747_p0.jpg",
      "path": "uploads/2026/06/ff7aa921.jpg",
      "size": 746621,
      "width": 827,
      "height": 1002,
      "mimeType": "image/jpeg",
      "hash": "744178d156482cbbdb988987bd8b26ee21919209c8a59b78b547e696779669cf",
      "uploaderLogin": "system",
      "createdAt": "2026-06-28T17:27:15.866Z",
      "isPublic": true,
      "title": "機動物：アサルトシャークシリーズ",
      "tags": [
        "機動物",
        "オリジナル",
        "サメ",
        "タンクシャーク",
        "メタルマックス"
      ],
      "sourceProvider": "pixiv",
      "sourceId": "146298747_p0",
      "sourcePageUrl": "https://www.pixiv.net/artworks/146298747",
      "sourceCreatedAt": "2026-06-21T15:00:22.000Z"
    },
    {
      "id": "f0372232",
      "filename": "crawl_src_mqwjeg05_1_1782665046762.webp",
      "path": "uploads/2026/06/8e9f54f7.webp",
      "size": 1027624,
      "width": 2591,
      "height": 3624,
      "mimeType": "image/webp",
      "hash": "6956ece1cad24518883523120a981bde1ffc3f56c8232c9795566a40fd895c35",
      "uploaderLogin": "system",
      "createdAt": "2026-06-28T16:44:27.611Z",
      "isPublic": true
    },
    {
      "id": "e8f29cdb",
      "filename": "crawl_src_new_004_1782664664512.webp",
      "path": "uploads/2026/06/3419ff00.webp",
      "size": 707144,
      "width": 3840,
      "height": 2160,
      "mimeType": "image/webp",
      "hash": "d0675a4b87f48f1a5f82576fc37725380d4c1aea98a7407144ab1d8ad4b80e5f",
      "uploaderLogin": "system",
      "createdAt": "2026-06-28T16:37:54.883Z",
      "isPublic": true
    },
    {
      "id": "a841a7cd",
      "filename": "crawl_src_mqwjeg06_t_1782664476844.jpg",
      "path": "uploads/2026/06/cde79100.jpg",
      "size": 4267571,
      "width": 2508,
      "height": 3541,
      "mimeType": "image/jpeg",
      "hash": "9730e2b0ce9a8a4188e9d2da2b2af7ae393f2bb09892a6f93677244db124f04a",
      "uploaderLogin": "system",
      "createdAt": "2026-06-28T16:34:57.277Z",
      "isPublic": true
    },
    {
      "id": "ead8d369",
      "filename": "crawl_src_new_003_1782658792036.webp",
      "path": "uploads/2026/06/5bd98889.webp",
      "size": 150036,
      "width": 967,
      "height": 1200,
      "mimeType": "image/webp",
      "hash": "d01055c6db569dce238fa979156912b322373707f65cbc76056b212d40751389",
      "uploaderLogin": "system",
      "createdAt": "2026-06-28T14:59:55.243Z",
      "isPublic": true
    },
    {
      "id": "dc476fb2",
      "filename": "pixiv_146289692_p0.jpg",
      "path": "uploads/2026/06/a3dc8e07.jpg",
      "size": 163256,
      "width": 1200,
      "height": 675,
      "mimeType": "image/jpeg",
      "hash": "5f4de274e4472045964edb449bb423531f765041665618c11e1d27c129a2b27f",
      "uploaderLogin": "system",
      "createdAt": "2026-06-28T14:58:43.646Z",
      "isPublic": true,
      "title": "【UTAUカバー】怪電話【コールセンター & 八八八三三】",
      "tags": [
        "UTAU",
        "コールセンター(UTAU)",
        "八八八三三",
        "怪電話"
      ],
      "sourceProvider": "pixiv",
      "sourceId": "146289692_p0",
      "sourcePageUrl": "https://www.pixiv.net/artworks/146289692",
      "sourceCreatedAt": "2026-06-21T12:15:59.000Z"
    },
    {
      "id": "bd1bc2da",
      "filename": "pixiv_146336705_p0.jpg",
      "path": "uploads/2026/06/3fe8625e.jpg",
      "size": 508401,
      "width": 1200,
      "height": 811,
      "mimeType": "image/jpeg",
      "hash": "4ef6c5121e288acb9bd6b8c55a38030039ec42024b3575629d9f869355b1430f",
      "uploaderLogin": "system",
      "createdAt": "2026-06-28T14:58:37.653Z",
      "isPublic": true,
      "title": "2026コナンまとめ_1",
      "tags": [
        "名探偵コナン",
        "江戸川コナン",
        "萩原千速",
        "神奈川県警",
        "長野県警",
        "緋色組",
        "クロスオーバー",
        "青山作品1000users入り"
      ],
      "sourceProvider": "pixiv",
      "sourceId": "146336705_p0",
      "sourcePageUrl": "https://www.pixiv.net/artworks/146336705",
      "sourceCreatedAt": "2026-06-22T14:33:43.000Z"
    },
    {
      "id": "d15b92fe",
      "filename": "crawl_src_new_003_1782658689802.webp",
      "path": "uploads/2026/06/d1a028b7.webp",
      "size": 321910,
      "width": 1657,
      "height": 2560,
      "mimeType": "image/webp",
      "hash": "9767e2721e593602d91bb36ea1465d1d431ce8dda6b5d9a0d091d4bf115f142c",
      "uploaderLogin": "system",
      "createdAt": "2026-06-28T14:58:17.795Z",
      "isPublic": true
    },
    {
      "id": "d32ce887",
      "filename": "crawl_src_mqwjeg05_1_1782655115936.webp",
      "path": "uploads/2026/06/4aa071bb.webp",
      "size": 1398692,
      "width": 900,
      "height": 1273,
      "mimeType": "image/webp",
      "hash": "c5d2497f920d8a721cc22325f7a4a983d7036289a64e2fb89723a3eddd1ad011",
      "uploaderLogin": "system",
      "createdAt": "2026-06-28T13:58:45.837Z",
      "isPublic": true
    },
    {
      "id": "7a6ebf54",
      "filename": "crawl_src_mqwjeg06_t_1782655049974.jpg",
      "path": "uploads/2026/06/8de7efcc.jpg",
      "size": 1266116,
      "width": 1447,
      "height": 1943,
      "mimeType": "image/jpeg",
      "hash": "28754b918267f4fefa03dd8139a07ac382e62df9948f87c9aa1cafa78cd4c88f",
      "uploaderLogin": "system",
      "createdAt": "2026-06-28T13:57:43.670Z",
      "isPublic": true
    },
    {
      "id": "e43adfa5",
      "filename": "crawl_src_mqwjeg05_1_1782650735423.webp",
      "path": "uploads/2026/06/7ea31260.webp",
      "size": 217138,
      "mimeType": "image/webp",
      "hash": "9014069ee460433f5d5f83e2c9c114728f02594ae7ff08955b4fd26beeaef56e",
      "uploaderLogin": "system",
      "createdAt": "2026-06-28T12:45:49.903Z",
      "isPublic": true
    },
    {
      "id": "d6becfa3",
      "filename": "crawl_src_mqwjeg05_1_1782650676242.webp",
      "path": "uploads/2026/06/8ec68ba5.webp",
      "size": 133942,
      "mimeType": "image/webp",
      "hash": "9678bde83cd54480e164b763a6374648f87fa77dafd58382373cfb09a0092802",
      "uploaderLogin": "system",
      "createdAt": "2026-06-28T12:44:53.392Z",
      "isPublic": true
    },
    {
      "id": "5c2cc48d",
      "filename": "crawl_src_new_003_1782650471726.webp",
      "path": "uploads/2026/06/157ca80c.webp",
      "size": 208006,
      "mimeType": "image/webp",
      "hash": "5886dca3fb7ed602c11f08926a37c11332e753362e901ff6b5b832d0d8e23847",
      "uploaderLogin": "system",
      "createdAt": "2026-06-28T12:41:20.004Z",
      "isPublic": true
    },
    {
      "id": "ed9c2db2",
      "filename": "crawl_src_new_003_1782647631194.webp",
      "path": "uploads/2026/06/409056b9.webp",
      "size": 221424,
      "mimeType": "image/webp",
      "hash": "bd8d6b62b629d18be41850b9c49643f375c03337d6acfe76cc7a81b1e83e94c1",
      "uploaderLogin": "system",
      "createdAt": "2026-06-28T11:53:53.421Z",
      "isPublic": true
    },
    {
      "id": "4e8d18dc",
      "filename": "crawl_src_mqwjeg05_8_1782647587593.jpg",
      "path": "uploads/2026/06/81a86503.jpg",
      "size": 508166,
      "mimeType": "image/jpeg",
      "hash": "b5605de7ed4d02dd4ce202c2a16f87756395948064c074a27947fcf18e39c9de",
      "uploaderLogin": "system",
      "createdAt": "2026-06-28T11:53:19.543Z",
      "isPublic": true
    },
    {
      "id": "a38762d6",
      "filename": "crawl_src_mqwjeg05_8_1782647327863.jpg",
      "path": "uploads/2026/06/b2475bd0.jpg",
      "size": 956728,
      "mimeType": "image/jpeg",
      "hash": "76928d1cf8a22da66153fb643fab3605a3d1dad06bd11b4b19db15504f6d800d",
      "uploaderLogin": "system",
      "createdAt": "2026-06-28T11:49:07.601Z",
      "isPublic": true
    },
    {
      "id": "61d19fa4",
      "filename": "pixiv_146475664_p0.jpg",
      "path": "uploads/2026/06/960b5c91.jpg",
      "size": 732522,
      "mimeType": "image/jpeg",
      "hash": "d009ba071349b8bcd309950bd761519a962f30c6e7dad11cc9b6a9f56af4c35d",
      "uploaderLogin": "system",
      "createdAt": "2026-06-28T11:47:31.411Z",
      "isPublic": true,
      "title": "「遅刻っスよ、先輩💢」",
      "tags": [
        "女の子",
        "オリジナル",
        "後輩ちゃん",
        "デート",
        "しゃがみ",
        "ニーソ",
        "待ち合わせ",
        "貧乳",
        "ジト目"
      ],
      "sourceProvider": "pixiv",
      "sourceId": "146475664_p0",
      "sourcePageUrl": "https://www.pixiv.net/artworks/146475664",
      "sourceCreatedAt": "2026-06-26T09:03:11.000Z"
    },
    {
      "id": "0a039b9b",
      "filename": "crawl_src_mqwjeg05_1_1782647230264.webp",
      "path": "uploads/2026/06/f1941bad.webp",
      "size": 177338,
      "mimeType": "image/webp",
      "hash": "8a924917c8f0d1be1a7334a710abfc44d1056836a69202f6dd9e02176e70ffae",
      "uploaderLogin": "system",
      "createdAt": "2026-06-28T11:47:16.159Z",
      "isPublic": true
    },
    {
      "id": "c7e73227",
      "filename": "pixiv_145425203_p0.jpg",
      "path": "uploads/2026/06/3d7383f9.jpg",
      "size": 992594,
      "mimeType": "image/jpeg",
      "hash": "27a6a62067ee3fedfda54de131c5fad6c87befb1a723f7083546cd27742f7056",
      "uploaderLogin": "system",
      "createdAt": "2026-06-28T11:46:48.382Z",
      "isPublic": true,
      "title": "老资历2",
      "tags": [
        "女の子",
        "欧派",
        "尻神様",
        "丝袜",
        "原神",
        "莫娜",
        "魔女帽子",
        "アストローギスト・モナ・メギストス",
        "ツインテ",
        "原神5000users入り"
      ],
      "sourceProvider": "pixiv",
      "sourceId": "145425203_p0",
      "sourcePageUrl": "https://www.pixiv.net/artworks/145425203",
      "sourceCreatedAt": "2026-05-31T03:34:37.000Z"
    },
    {
      "id": "2e83dded",
      "filename": "crawl_src_new_003_1782647166289.webp",
      "path": "uploads/2026/06/17858666.webp",
      "size": 535950,
      "mimeType": "image/webp",
      "hash": "facf0cc32201893aee3728899e0bcea2e52a0bda0b02021e3a0bfd2b48ca68ba",
      "uploaderLogin": "system",
      "createdAt": "2026-06-28T11:46:10.851Z",
      "isPublic": true
    },
    {
      "id": "f365f6f4",
      "filename": "crawl_src_new_003_1782647165768.webp",
      "path": "uploads/2026/06/70a0c004.webp",
      "size": 228058,
      "mimeType": "image/webp",
      "hash": "f306c0b611bd07ffc830d99155af820011318a13af2e09cefa52ed3908df1dfc",
      "uploaderLogin": "system",
      "createdAt": "2026-06-28T11:46:07.914Z",
      "isPublic": true
    },
    {
      "id": "df93572c",
      "filename": "crawl_src_new_002_1782641453959_3.webp",
      "path": "uploads/2026/06/df93572c.webp",
      "size": 1670460,
      "mimeType": "image/webp",
      "hash": "cd1a6ffa714cbd38648495440c9748ed3ecab3ecf039cf2e2e6a3d2136f80cf1",
      "uploaderLogin": "system",
      "createdAt": "2026-06-28T10:10:54.296Z",
      "isPublic": true
    },
    {
      "id": "f939853d",
      "filename": "crawl_src_new_003_1782641329707_4.webp",
      "path": "uploads/2026/06/f939853d.webp",
      "size": 425456,
      "mimeType": "image/webp",
      "hash": "eedaa92bfe229c5da7a9d697c5c4db802838aa4f9cf73d0001dd340a37eb4f0c",
      "uploaderLogin": "system",
      "createdAt": "2026-06-28T10:08:49.976Z",
      "isPublic": true
    },
    {
      "id": "1d272dd7",
      "filename": "crawl_src_mqwjeg05_8_1782631891617_4.jpeg",
      "path": "uploads/2026/06/1d272dd7.jpg",
      "size": 978966,
      "mimeType": "image/jpeg",
      "hash": "d6e4ca5a243b2f2f11f49a09fbf4f7a66a13d18480c02dd776cfec98a55d58ce",
      "uploaderLogin": "system",
      "createdAt": "2026-06-28T07:31:31.877Z",
      "isPublic": true
    },
    {
      "id": "d9f4d816",
      "filename": "crawl_src_mqwjeg05_1_1782631689275_4.webp",
      "path": "uploads/2026/06/d9f4d816.webp",
      "size": 407088,
      "mimeType": "image/webp",
      "hash": "5ebdd67c34351fe9e8b700c34b8215cec5a4afc92eba6055e3155ef4405e19c8",
      "uploaderLogin": "system",
      "createdAt": "2026-06-28T07:28:09.535Z",
      "isPublic": true
    },
    {
      "id": "700030f4",
      "filename": "crawl_src_new_004_1782631656894_2.webp",
      "path": "uploads/2026/06/700030f4.webp",
      "size": 1281428,
      "mimeType": "image/webp",
      "hash": "1c75f004f6f32a6dd778be732cbf60fd7a7331f3e810aca27a9985ba63c98aa1",
      "uploaderLogin": "system",
      "createdAt": "2026-06-28T07:27:37.152Z",
      "isPublic": true
    },
    {
      "id": "c40daf2c",
      "filename": "crawl_src_mqwjeg06_t_1782631410454_3.jpeg",
      "path": "uploads/2026/06/c40daf2c.jpg",
      "size": 5211763,
      "mimeType": "image/jpeg",
      "hash": "36b3b87c5502c263a6a11d63eeab4f0321f4d392e20dde6381c914b956a2ced5",
      "uploaderLogin": "system",
      "createdAt": "2026-06-28T07:23:30.724Z",
      "isPublic": true
    },
    {
      "id": "fe451dfa",
      "filename": "crawl_src_new_001_1782627850289_1.jpeg",
      "path": "uploads/2026/06/fe451dfa.jpg",
      "size": 226501,
      "mimeType": "image/jpeg",
      "hash": "333107f3e93d80f0bd52f30a8e2c5b2ba1bc10c70032f7d118e395d639877bd3",
      "uploaderLogin": "system",
      "createdAt": "2026-06-28T06:24:10.567Z",
      "isPublic": true
    },
    {
      "id": "23acf6cd",
      "filename": "crawl_src_new_001_1782627768957_3.jpeg",
      "path": "uploads/2026/06/23acf6cd.jpg",
      "size": 174346,
      "mimeType": "image/jpeg",
      "hash": "43aaaca746940648a92683ac312e726f91df68bc08843805cd7f52d9f754f279",
      "uploaderLogin": "system",
      "createdAt": "2026-06-28T06:22:49.212Z",
      "isPublic": true
    },
    {
      "id": "e39e9c74",
      "filename": "crawl_src_new_004_1782625174322_0.webp",
      "path": "uploads/2026/06/e39e9c74.webp",
      "size": 1001102,
      "mimeType": "image/webp",
      "hash": "185215d640ebc792f5db9fbc28f406666187221480b2a7b2880781e19e3b7370",
      "uploaderLogin": "system",
      "createdAt": "2026-06-28T05:39:34.598Z",
      "isPublic": true,
      "width": 3456,
      "height": 1943
    },
    {
      "id": "42ee6006",
      "filename": "crawl_src_new_001_1782624953196_2.jpeg",
      "path": "uploads/2026/06/42ee6006.jpg",
      "size": 355768,
      "mimeType": "image/jpeg",
      "hash": "8300112ca7ed6e4afbeb0bf38894fab0f2fa90173b9fe5060cc096787f9d66c7",
      "uploaderLogin": "system",
      "createdAt": "2026-06-28T05:35:53.421Z",
      "isPublic": true,
      "width": 1920,
      "height": 1080
    },
    {
      "id": "01b1d36d",
      "filename": "crawl_src_new_004_1782624139980_4.webp",
      "path": "uploads/2026/06/01b1d36d.webp",
      "size": 1171908,
      "mimeType": "image/webp",
      "hash": "7950e0c96cdfe0d45c9b29cb14bab1f82fcc940ed684d705730604dfce256740",
      "uploaderLogin": "system",
      "createdAt": "2026-06-28T05:22:20.296Z",
      "isPublic": true,
      "width": 7680,
      "height": 4320
    },
    {
      "id": "e6abe6b8",
      "filename": "crawl_src_mqwjeg05_8_1782621792170_4.jpeg",
      "path": "uploads/2026/06/e6abe6b8.jpg",
      "size": 592844,
      "mimeType": "image/jpeg",
      "hash": "d29e2239e23b74af197c0728dad24a7be93621a2efc68a07f5bd3e8211658415",
      "uploaderLogin": "system",
      "createdAt": "2026-06-28T04:43:12.537Z",
      "isPublic": true,
      "width": 1986,
      "height": 1241
    },
    {
      "id": "83d09650",
      "filename": "crawl_src_new_002_1782621646777_3.webp",
      "path": "uploads/2026/06/83d09650.webp",
      "size": 222230,
      "mimeType": "image/webp",
      "hash": "27237a7c6e31b4b585c980df7258758ef7d588de1d9d78c440f98fc95da9cd65",
      "uploaderLogin": "system",
      "createdAt": "2026-06-28T04:40:47.032Z",
      "isPublic": true,
      "width": 4800,
      "height": 2700
    },
    {
      "id": "ebfdcd31",
      "filename": "crawl_src_mqwjeg05_1_1782621032952_1.webp",
      "path": "uploads/2026/06/ebfdcd31.webp",
      "size": 227940,
      "mimeType": "image/webp",
      "hash": "386796a2942f0bde490f99baecedb383dfbe3e79787887da53aaad9c08a6edff",
      "uploaderLogin": "system",
      "createdAt": "2026-06-28T04:30:33.197Z",
      "isPublic": true,
      "width": 1875,
      "height": 2622
    },
    {
      "id": "e01ea716",
      "filename": "crawl_src_new_004_1782620964631_4.webp",
      "path": "uploads/2026/06/e01ea716.webp",
      "size": 1366076,
      "mimeType": "image/webp",
      "hash": "d8a7165260ae9a45ddbb805bfb0e271669949cd970f4e3913bde95275d9b9ac6",
      "uploaderLogin": "system",
      "createdAt": "2026-06-28T04:29:24.847Z",
      "isPublic": true,
      "width": 7996,
      "height": 4716
    },
    {
      "id": "fcbb973a",
      "filename": "crawl_src_mqwjeg06_t_1782618369548_3.jpeg",
      "path": "uploads/2026/06/fcbb973a.jpg",
      "size": 1310586,
      "mimeType": "image/jpeg",
      "hash": "a86192a04a7224345c8a1ee5d863d607852b38a218f8cee6d6d043e16fe9edfb",
      "uploaderLogin": "system",
      "createdAt": "2026-06-28T03:46:09.807Z",
      "isPublic": true,
      "width": 956,
      "height": 1403
    },
    {
      "id": "19be8bdd",
      "filename": "crawl_src_mqwjeg05_8_1782618159645_3.jpeg",
      "path": "uploads/2026/06/19be8bdd.jpg",
      "size": 1140174,
      "mimeType": "image/jpeg",
      "hash": "ddbc027caee05e44ded0a3ccf9554f74af858e90e9d11e81006a89ac3496f697",
      "uploaderLogin": "system",
      "createdAt": "2026-06-28T03:42:39.895Z",
      "isPublic": true,
      "width": 1920,
      "height": 1080
    },
    {
      "id": "286bf19f",
      "filename": "crawl_src_mqwjeg05_1_1782617199371_1.webp",
      "path": "uploads/2026/06/286bf19f.webp",
      "size": 150632,
      "mimeType": "image/webp",
      "hash": "67035b1c0eaa90d02e23f982b097892018252edc6545a09500a2a0705e8bf40d",
      "uploaderLogin": "system",
      "createdAt": "2026-06-28T03:26:39.570Z",
      "isPublic": true,
      "width": 1587,
      "height": 2257
    },
    {
      "id": "1d13923c",
      "filename": "crawl_src_new_001_1782582178965_1.jpeg",
      "path": "uploads/2026/06/1d13923c.jpg",
      "size": 192909,
      "mimeType": "image/jpeg",
      "hash": "3f74d329f184fda5ee42ef62d5b30a2e55cafd4366f79cadd2ca19a27f07e030",
      "uploaderLogin": "system",
      "createdAt": "2026-06-27T17:42:59.179Z",
      "isPublic": true,
      "width": 1920,
      "height": 1080
    },
    {
      "id": "d4aab8a7",
      "filename": "crawl_src_mqwjeg05_1_1782576764309.webp",
      "path": "uploads/2026/06/d4aab8a7.webp",
      "size": 166142,
      "mimeType": "image/webp",
      "hash": "282eda63e7f0e5a8fcee839caa18374d60b9447ab56e1d9d538a4d825fcde27c",
      "uploaderLogin": "system",
      "createdAt": "2026-06-27T16:12:44.541Z",
      "isPublic": true,
      "width": 1666,
      "height": 2500
    },
    {
      "id": "c8ade9cc",
      "filename": "crawl_src_mqwjeg05_1_1782575668362.webp",
      "path": "uploads/2026/06/c8ade9cc.webp",
      "size": 119362,
      "mimeType": "image/webp",
      "hash": "bd41c4613883e58f732c125dbe835bcb4e5f20973f565a9af135e77d26b9a750",
      "uploaderLogin": "system",
      "createdAt": "2026-06-27T15:54:28.607Z",
      "isPublic": true,
      "width": 1535,
      "height": 2201
    },
    {
      "id": "4aaf31a6",
      "filename": "crawl_src_mqwjeg05_1_1782575508794.webp",
      "path": "uploads/2026/06/4aaf31a6.webp",
      "size": 289122,
      "mimeType": "image/webp",
      "hash": "bc1d3adda539397e4b10df7330370a53ce8fc0900069c9f74974da2bf1ffd780",
      "uploaderLogin": "system",
      "createdAt": "2026-06-27T15:51:49.037Z",
      "isPublic": true,
      "width": 2270,
      "height": 4000
    },
    {
      "id": "1bcdb217",
      "filename": "img_12.jpg",
      "path": "uploads/2026/06/1bcdb217.webp",
      "size": 45139,
      "width": 569,
      "height": 881,
      "mimeType": "image/jpeg",
      "hash": "1bcdb21743f949fce78406c394e5ecd02aae9aa83c0ffe384e01587d1f8a9df3",
      "uploaderLogin": "2982136527",
      "createdAt": "2026-06-27T07:52:00.000Z"
    }
  ]
}