{
  "version": 1,
  "strategy": "id_hash_mod_32",
  "shardCount": 32,
  "legacyPath": "data/images.json",
  "migratedAt": "2026-06-29T04:43:50.241Z",
  "shards": [
    {
      "id": "00",
      "path": "data/images-shards/00.json",
      "imageCount": 155,
      "updatedAt": "2026-06-30T18:53:35.386Z"
    },
    {
      "id": "01",
      "path": "data/images-shards/01.json",
      "imageCount": 159,
      "updatedAt": "2026-06-30T18:53:33.352Z"
    },
    {
      "id": "02",
      "path": "data/images-shards/02.json",
      "imageCount": 157,
      "updatedAt": "2026-06-30T18:55:47.022Z"
    },
    {
      "id": "03",
      "path": "data/images-shards/03.json",
      "imageCount": 149,
      "updatedAt": "2026-06-30T18:55:56.574Z"
    },
    {
      "id": "04",
      "path": "data/images-shards/04.json",
      "imageCount": 156,
      "updatedAt": "2026-06-30T18:52:39.584Z"
    },
    {
      "id": "05",
      "path": "data/images-shards/05.json",
      "imageCount": 146,
      "updatedAt": "2026-06-30T18:47:11.809Z"
    },
    {
      "id": "06",
      "path": "data/images-shards/06.json",
      "imageCount": 139,
      "updatedAt": "2026-06-30T18:51:32.623Z"
    },
    {
      "id": "07",
      "path": "data/images-shards/07.json",
      "imageCount": 159,
      "updatedAt": "2026-06-30T18:55:09.502Z"
    },
    {
      "id": "08",
      "path": "data/images-shards/08.json",
      "imageCount": 163,
      "updatedAt": "2026-06-30T18:49:20.400Z"
    },
    {
      "id": "09",
      "path": "data/images-shards/09.json",
      "imageCount": 159,
      "updatedAt": "2026-06-30T18:54:54.672Z"
    },
    {
      "id": "0a",
      "path": "data/images-shards/0a.json",
      "imageCount": 162,
      "updatedAt": "2026-06-30T18:52:25.805Z"
    },
    {
      "id": "0b",
      "path": "data/images-shards/0b.json",
      "imageCount": 139,
      "updatedAt": "2026-06-30T18:55:57.335Z"
    },
    {
      "id": "0c",
      "path": "data/images-shards/0c.json",
      "imageCount": 151,
      "updatedAt": "2026-06-30T18:53:40.668Z"
    },
    {
      "id": "0d",
      "path": "data/images-shards/0d.json",
      "imageCount": 149,
      "updatedAt": "2026-06-30T18:55:00.408Z"
    },
    {
      "id": "0e",
      "path": "data/images-shards/0e.json",
      "imageCount": 157,
      "updatedAt": "2026-06-30T18:53:25.351Z"
    },
    {
      "id": "0f",
      "path": "data/images-shards/0f.json",
      "imageCount": 168,
      "updatedAt": "2026-06-30T18:52:45.424Z"
    },
    {
      "id": "10",
      "path": "data/images-shards/10.json",
      "imageCount": 138,
      "updatedAt": "2026-06-30T18:52:50.110Z"
    },
    {
      "id": "11",
      "path": "data/images-shards/11.json",
      "imageCount": 172,
      "updatedAt": "2026-06-30T18:55:51.438Z"
    },
    {
      "id": "12",
      "path": "data/images-shards/12.json",
      "imageCount": 146,
      "updatedAt": "2026-06-30T18:55:02.833Z"
    },
    {
      "id": "13",
      "path": "data/images-shards/13.json",
      "imageCount": 138,
      "updatedAt": "2026-06-30T18:55:55.068Z"
    },
    {
      "id": "14",
      "path": "data/images-shards/14.json",
      "imageCount": 164,
      "updatedAt": "2026-06-30T18:55:11.285Z"
    },
    {
      "id": "15",
      "path": "data/images-shards/15.json",
      "imageCount": 158,
      "updatedAt": "2026-06-30T15:51:58.614Z"
    },
    {
      "id": "16",
      "path": "data/images-shards/16.json",
      "imageCount": 156,
      "updatedAt": "2026-06-30T18:55:48.788Z"
    },
    {
      "id": "17",
      "path": "data/images-shards/17.json",
      "imageCount": 166,
      "updatedAt": "2026-06-30T18:55:46.276Z"
    },
    {
      "id": "18",
      "path": "data/images-shards/18.json",
      "imageCount": 160,
      "updatedAt": "2026-06-30T18:53:41.321Z"
    },
    {
      "id": "19",
      "path": "data/images-shards/19.json",
      "imageCount": 177,
      "updatedAt": "2026-06-30T18:54:57.493Z"
    },
    {
      "id": "1a",
      "path": "data/images-shards/1a.json",
      "imageCount": 142,
      "updatedAt": "2026-06-30T18:55:52.271Z"
    },
    {
      "id": "1b",
      "path": "data/images-shards/1b.json",
      "imageCount": 168,
      "updatedAt": "2026-06-30T18:52:28.991Z"
    },
    {
      "id": "1c",
      "path": "data/images-shards/1c.json",
      "imageCount": 160,
      "updatedAt": "2026-06-30T18:51:25.128Z"
    },
    {
      "id": "1d",
      "path": "data/images-shards/1d.json",
      "imageCount": 158,
      "updatedAt": "2026-06-30T18:52:33.176Z"
    },
    {
      "id": "1e",
      "path": "data/images-shards/1e.json",
      "imageCount": 166,
      "updatedAt": "2026-06-30T18:45:07.180Z"
    },
    {
      "id": "1f",
      "path": "data/images-shards/1f.json",
      "imageCount": 166,
      "updatedAt": "2026-06-30T18:55:05.901Z"
    }
  ]
}